GraphSL/Evaluation.py
GraphSL/Prescribed.py
GraphSL/__init__.py
GraphSL/utils.py
GraphSL/GNN/__init__.py
GraphSL/GNN/GCNSI/__init__.py
GraphSL/GNN/GCNSI/main.py
GraphSL/GNN/GCNSI/model.py
GraphSL/GNN/IVGD/__init__.py
GraphSL/GNN/IVGD/correction.py
GraphSL/GNN/IVGD/diffusion_model.py
GraphSL/GNN/IVGD/earlystopping.py
GraphSL/GNN/IVGD/i_deepis.py
GraphSL/GNN/IVGD/main.py
GraphSL/GNN/IVGD/preprocessing.py
GraphSL/GNN/IVGD/training.py
GraphSL/GNN/IVGD/validity_net.py
GraphSL/GNN/IVGD/model/MLP.py
GraphSL/GNN/IVGD/model/__init__.py
GraphSL/GNN/SLVAE/__init__.py
GraphSL/GNN/SLVAE/main.py
GraphSL/GNN/SLVAE/model.py
GraphSL-0.15.dist-info/LICENSE
GraphSL-0.15.dist-info/METADATA
GraphSL-0.15.dist-info/WHEEL
GraphSL-0.15.dist-info/top_level.txt
GraphSL-0.15.dist-info/RECORD
